tower_cli-0.3.3.dist-info/METADATA
tower_cli-0.3.3.dist-info/WHEEL
tower_cli-0.3.3.dist-info/licenses/LICENSE
tower/__main__.py
tower/client.py
tower/__init__.py
tower/tower_api_client/models/accept_invitation_response.py
tower/tower_api_client/models/list_my_team_invitations_response.py
tower/tower_api_client/models/generate_run_statistics_response.py
tower/tower_api_client/models/generate_app_statistics_response.py
tower/tower_api_client/models/update_my_team_invitation_response.py
tower/tower_api_client/models/delete_api_key_params.py
tower/tower_api_client/models/list_api_keys_response.py
tower/tower_api_client/models/get_run_logs_output_body.py
tower/tower_api_client/models/parameter.py
tower/tower_api_client/models/resend_team_invitation_response.py
tower/tower_api_client/models/team_invitation.py
tower/tower_api_client/models/remove_team_member_params.py
tower/tower_api_client/models/create_app_params.py
tower/tower_api_client/models/run_results.py
tower/tower_api_client/models/resend_team_invitation_params.py
tower/tower_api_client/models/user.py
tower/tower_api_client/models/claim_device_login_ticket_response.py
tower/tower_api_client/models/run_app_response.py
tower/tower_api_client/models/invite_team_member_response.py
tower/tower_api_client/models/account.py
tower/tower_api_client/models/list_runs_response.py
tower/tower_api_client/models/describe_secrets_key_response.py
tower/tower_api_client/models/token.py
tower/tower_api_client/models/update_account_slug_params.py
tower/tower_api_client/models/update_account_slug_response.py
tower/tower_api_client/models/api_key.py
tower/tower_api_client/models/create_api_key_params.py
tower/tower_api_client/models/delete_team_response.py
tower/tower_api_client/models/list_team_invitations_response.py
tower/tower_api_client/models/list_app_environments_response.py
tower/tower_api_client/models/create_account_params_flags_struct.py
tower/tower_api_client/models/delete_team_invitation_response.py
tower/tower_api_client/models/create_account_params.py
tower/tower_api_client/models/app.py
tower_cli-0.3.3.dist-info/RECORD
